pytest_pinpoint.py
pytest_pinpoint-0.3.0.dist-info/LICENSE
pytest_pinpoint-0.3.0.dist-info/METADATA
pytest_pinpoint-0.3.0.dist-info/WHEEL
pytest_pinpoint-0.3.0.dist-info/entry_points.txt
pytest_pinpoint-0.3.0.dist-info/top_level.txt
pytest_pinpoint-0.3.0.dist-info/RECORD
