Metadata-Version: 2.1
Name: pytest-pinpoint
Version: 0.3.0
Summary: A pytest plugin which runs SBFL algorithms to detect faults.
Home-page: https://github.com/Generalized-SBFL/pytest-pinpoint
Author: Lancaster Wu
Author-email: wuj@allegheny.edu
License: GNU
Platform: any
Requires-Dist: coverage (>=5.1)
Requires-Dist: pytest (>=4.4.0)
Requires-Dist: pytest-cov
